launchpad/__init__.py
launchpad/constants.py
launchpad/core.py
launchpad-2.0.1.dist-info/LICENSE
launchpad-2.0.1.dist-info/METADATA
launchpad-2.0.1.dist-info/WHEEL
launchpad-2.0.1.dist-info/top_level.txt
launchpad-2.0.1.dist-info/RECORD
