Metadata-Version: 2.1
Name: launchpad
Version: 2.0.1
Summary: Launchpad represents a small factory and a distinct abstract for defining actionable items
Home-page: https://github.com/mikemalinowski/launchpad
Author: Mike Malinowski
Author-email: mike.malinowski@outlook.com
Keywords: launch launchpad pad action actions
Classifier: Programming Language :: Python
Classifier: License :: OSI Approved :: MIT License
Classifier: Operating System :: OS Independent
License-File: LICENSE
Requires-Dist: qute
Requires-Dist: scribble
Requires-Dist: factories
